[{"pet_name":"Charlie","pet_type":"fish","pet_img":"bird.jpg","user_id":"dTOK3zKY","specail_details":"confidential"},
{"pet_name":"Lucy","pet_type":"bird","pet_img":"rabbit.jpg","user_id":"F099bjad","specail_details":"restricted"},
{"pet_name":"Rocky","pet_type":"dog","pet_img":"rabbit.jpg","user_id":"AE8oJU2V","specail_details":"important"},
{"pet_name":"Sadie","pet_type":"hamster","pet_img":"rabbit.jpg","user_id":"4Hp9c07B","specail_details":"restricted"},
{"pet_name":"Lola","pet_type":"cat","pet_img":"dog.jpg","user_id":"yzfy3MJ3","specail_details":"restricted"}]